{
  "video_name": "41_conclusion.mp4",
  "teaching_stage": "conclusion",
  "subject": "math",
  "teaching_goal": "Understand the method of retaining the first and last terms in an arithmetic sequence; master the strategy of eliminating intermediate terms by observing the difference between two equations.",
  "transcript": "[726.2855 -> 772.26] 老师要提示大家在等差数列中啊我们是保留了一个世纪中的首相和伟相那么既然现在我们要研究的是世与世之间的关系我们不妨考虑保留这个首相保留这个尾相大家思考那边的小组举手了那么请你们来分享一下你们是怎样思考这个问题的呢非常好这边小组的同学说他们观察之后发现现在我们要保留的是这两项那么要消去中间项我们纵向来看两个式子之间相差着这样一个Q所以我们只需在左右两式式子二式左右两边同尘上Q那么我们就能发现这个时候中间这两对它是完全相同的我们可以将它进行消去那么消去之后一式和二式联力相减SN减Q倍的SN就等于首项A减保留的尾项Q的N减一字方好一项之后我们就得到这个时候SN就等于一减Q分之A乘一减Q的差这里我们要注意Q它是非常好不能等于一那么当Q等于一的时候呢这边同学这个时候啊其实就是N个A一的了。\n[775.7 -> 786.26] 时间到我来擦我来擦那游戏太好看了。",
  "visual_facts": "**Phase 4: Conclusion - Visual Knowledge Consolidation**\n\n1. **Summary Artifact (Static View)**:\n   - The main visual carrier of the summary is the blackboard, which contains a series of mathematical equations and derivations. The layout includes:\n     - A central equation: $S_n = a_1 \\frac{1-r^n}{1-r} + \\frac{r^n}{1-r}$\n     - Two derived equations labeled as (1) and (2).\n     - A final simplified equation: $S_n = \\frac{a_1(1-r^n)}{1-r}$\n\n2. **Key Knowledge Items (Content View)**:\n   - Main equation: $S_n = a_1 \\frac{1-r^n}{1-r} + \\frac{r^n}{1-r}$\n   - Derived equations:\n     - $S_n = a_1 + a_1r + \\ldots + a_1r^{n-1}$\n     - $rS_n = a_1r + a_1r^2 + \\ldots + a_1r^n$\n   - Simplified final equation: $S_n = \\frac{a_1(1-r^n)}{1-r}$\n   - Additional calculations: $S_n - rS_n = a_1 - a_1r^n$ and $S_n(1-r) = a_1(1-r^n)$\n\n3. **Review Gestures (Dynamic View)**:\n   - The teacher writes additional steps on the blackboard, including:\n     - $S_n(1-r) = a_1(1-r^n)$\n     - $S_n = \\frac{a_1(1-r^n)}{1-r}$\n   - The teacher points to each part of the equation as they write, emphasizing the transformation from $S_n - rS_n$ to the final simplified form.\n   - The teacher underlines the final equation $S_n = \\frac{a_1(1-r^n)}{1-r}$ to highlight it as the key takeaway.\n\n4. **Transition to Next Step**:\n   - The screen to the right displays a slide with text in Chinese, likely summarizing key points or providing further instructions. The visible text includes:\n     - \"复习与作业布置\" (Review and Homework Assignment)\n     - \"课堂小结\" (Class Summary)\n     - \"布置作业\" (Assign Homework)\n   - The slide includes bullet points and mathematical expressions, indicating areas for further study or homework tasks, though specific details are not fully visible.\n\nThis structured visual summary consolidates the lesson's key mathematical derivations, with the teacher's gestures reinforcing the logical flow and final conclusion.",
  "visual_narrative": "The lesson concludes with a blackboard summary centered on the derivation of the geometric series formula. The teacher visually reviews the content by writing and pointing to each step of the equation transformation, emphasizing the transition from $S_n - rS_n$ to the final simplified form. Finally, the visual focus shifts to the screen displaying homework instructions, signaling the end of the session.",
  "pedagogy_graph": {
    "nodes": [
      {
        "id": "c1",
        "label": "Arithmetic Sequence",
        "type": "Concept",
        "knowledge_type": "Fact",
        "timestamp": "[726.2855 -> 772.26]"
      },
      {
        "id": "c2",
        "label": "First Term Retention",
        "type": "Concept",
        "knowledge_type": "Principle",
        "timestamp": "[726.2855 -> 772.26]"
      },
      {
        "id": "c3",
        "label": "Last Term Retention",
        "type": "Concept",
        "knowledge_type": "Principle",
        "timestamp": "[726.2855 -> 772.26]"
      },
      {
        "id": "c4",
        "label": "Intermediate Term Elimination",
        "type": "Concept",
        "knowledge_type": "Procedure",
        "timestamp": "[726.2855 -> 772.26]"
      },
      {
        "id": "c5",
        "label": "Geometric Series Formula",
        "type": "Concept",
        "knowledge_type": "Fact",
        "timestamp": "[726.2855 -> 772.26]"
      },
      {
        "id": "c6",
        "label": "Equation Transformation",
        "type": "Concept",
        "knowledge_type": "Procedure",
        "timestamp": "[726.2855 -> 772.26]"
      },
      {
        "id": "c7",
        "label": "S_n = a_1 + a_1r + ... + a_1r^(n-1)",
        "type": "Concept",
        "knowledge_type": "Fact",
        "timestamp": "[726.2855 -> 772.26]"
      },
      {
        "id": "c8",
        "label": "rS_n = a_1r + a_1r^2 + ... + a_1r^n",
        "type": "Concept",
        "knowledge_type": "Fact",
        "timestamp": "[726.2855 -> 772.26]"
      },
      {
        "id": "c9",
        "label": "S_n - rS_n = a_1 - a_1r^n",
        "type": "Concept",
        "knowledge_type": "Fact",
        "timestamp": "[726.2855 -> 772.26]"
      },
      {
        "id": "c10",
        "label": "S_n(1-r) = a_1(1-r^n)",
        "type": "Concept",
        "knowledge_type": "Fact",
        "timestamp": "[726.2855 -> 772.26]"
      },
      {
        "id": "c11",
        "label": "S_n = (a_1(1-r^n))/(1-r)",
        "type": "Concept",
        "knowledge_type": "Fact",
        "timestamp": "[726.2855 -> 772.26]"
      },
      {
        "id": "v1",
        "label": "Blackboard with Equations",
        "type": "Visual",
        "original_text": "The blackboard contains equations: S_n = a_1 + a_1r + ... + a_1r^(n-1), rS_n = a_1r + a_1r^2 + ... + a_1r^n, and S_n = (a_1(1-r^n))/(1-r).",
        "ocr_corrected": true
      },
      {
        "id": "v2",
        "label": "Teacher Gestures",
        "type": "Visual",
        "original_text": "The teacher points to and underlines equations while explaining transformations.",
        "ocr_corrected": false
      },
      {
        "id": "v3",
        "label": "Slide with Homework Instructions",
        "type": "Visual",
        "original_text": "The slide displays 'Review and Homework Assignment' and 'Class Summary' in English.",
        "ocr_corrected": true
      },
      {
        "id": "s1",
        "label": "Group Brainstorming",
        "type": "Student_State",
        "cognitive_state": "Brainstorming"
      },
      {
        "id": "s2",
        "label": "Student Response",
        "type": "Student_State",
        "cognitive_state": "Answering"
      }
    ],
    "edges": [
      {
        "source": "c1",
        "target": "c2",
        "relation": "builds_upon",
        "intent": "The concept of arithmetic sequence builds upon the principle of retaining the first term."
      },
      {
        "source": "c1",
        "target": "c3",
        "relation": "builds_upon",
        "intent": "The concept of arithmetic sequence builds upon the principle of retaining the last term."
      },
      {
        "source": "c1",
        "target": "c4",
        "relation": "builds_upon",
        "intent": "The concept of arithmetic sequence builds upon the procedure of eliminating intermediate terms."
      },
      {
        "source": "c5",
        "target": "c6",
        "relation": "builds_upon",
        "intent": "The geometric series formula is derived through equation transformation."
      },
      {
        "source": "c7",
        "target": "c8",
        "relation": "evolves_from",
        "intent": "The equation rS_n evolves from the equation S_n by multiplying by r."
      },
      {
        "source": "c8",
        "target": "c9",
        "relation": "evolves_from",
        "intent": "The equation S_n - rS_n evolves from subtracting rS_n from S_n."
      },
      {
        "source": "c9",
        "target": "c10",
        "relation": "evolves_from",
        "intent": "The equation S_n(1-r) evolves from factoring out (1-r) from S_n - rS_n."
      },
      {
        "source": "c10",
        "target": "c11",
        "relation": "evolves_from",
        "intent": "The equation S_n = (a_1(1-r^n))/(1-r) evolves from dividing both sides of S_n(1-r) by (1-r)."
      },
      {
        "source": "v1",
        "target": "c11",
        "relation": "visualizes",
        "intent": "The blackboard visualizes the final equation S_n = (a_1(1-r^n))/(1-r)."
      },
      {
        "source": "v2",
        "target": "c6",
        "relation": "scaffolds",
        "intent": "The teacher's gestures scaffold the understanding of equation transformations."
      },
      {
        "source": "v3",
        "target": "c5",
        "relation": "summarizes",
        "intent": "The slide summarizes the geometric series formula and its applications."
      },
      {
        "source": "s1",
        "target": "c4",
        "relation": "engages_with",
        "intent": "Students brainstorm the procedure of eliminating intermediate terms."
      },
      {
        "source": "s2",
        "target": "c3",
        "relation": "engages_with",
        "intent": "Students respond to the principle of retaining the last term."
      }
    ]
  },
  "graph_generator_version": "pedagogy_graph_v7"
}